Topsis_AbhiroopSingh_102213027/__init__.py
Topsis_AbhiroopSingh_102213027/__main__.py
Topsis_AbhiroopSingh_102213027/topsis.py
Topsis_AbhiroopSingh_102213027-1.0.14.dist-info/METADATA
Topsis_AbhiroopSingh_102213027-1.0.14.dist-info/WHEEL
Topsis_AbhiroopSingh_102213027-1.0.14.dist-info/entry_points.txt
Topsis_AbhiroopSingh_102213027-1.0.14.dist-info/top_level.txt
Topsis_AbhiroopSingh_102213027-1.0.14.dist-info/RECORD
