Metadata-Version: 2.1
Name: Topsis_AbhiroopSingh_102213027
Version: 1.0.14
Summary: A python package for implementing topsis
Home-page: https://github.com/ASingh917/Topsis_102213027
Author: Abhiroop Singh
Author-email: asingh34_be22@thapar.edu
Classifier: Programming Language :: Python :: 3
Classifier: License :: OSI Approved :: MIT License
Classifier: Operating System :: OS Independent
Requires-Dist: pandas
Requires-Dist: numpy
